odoo/addons/vendor_pricelist_category/README.rst
odoo/addons/vendor_pricelist_category/__init__.py
odoo/addons/vendor_pricelist_category/__manifest__.py
odoo/addons/vendor_pricelist_category/i18n/es.po
odoo/addons/vendor_pricelist_category/models/__init__.py
odoo/addons/vendor_pricelist_category/models/product_supplierinfo.py
odoo/addons/vendor_pricelist_category/models/product_supplierinfo_category.py
odoo/addons/vendor_pricelist_category/readme/CONFIGURE.md
odoo/addons/vendor_pricelist_category/readme/CONTRIBUTORS.md
odoo/addons/vendor_pricelist_category/readme/DESCRIPTION.md
odoo/addons/vendor_pricelist_category/readme/USAGE.md
odoo/addons/vendor_pricelist_category/security/ir.model.access.csv
odoo/addons/vendor_pricelist_category/static/description/icon.png
odoo/addons/vendor_pricelist_category/static/description/index.html
odoo/addons/vendor_pricelist_category/tests/__init__.py
odoo/addons/vendor_pricelist_category/tests/test_vendor_pricelist_category.py
odoo/addons/vendor_pricelist_category/views/product_supplierinfo_category_view.xml
odoo/addons/vendor_pricelist_category/views/product_supplierinfo_views.xml
odoo_addon_vendor_pricelist_category-16.0.1.0.1.1.dist-info/METADATA
odoo_addon_vendor_pricelist_category-16.0.1.0.1.1.dist-info/WHEEL
odoo_addon_vendor_pricelist_category-16.0.1.0.1.1.dist-info/top_level.txt
odoo_addon_vendor_pricelist_category-16.0.1.0.1.1.dist-info/RECORD
