Metadata-Version: 2.1
Name: odoo-addon-vendor_pricelist_category
Version: 16.0.1.0.1.1
Requires-Python: >=3.10
Requires-Dist: odoo-addon-purchase_discount>=16.0dev,<16.1dev
Requires-Dist: odoo>=16.0a,<16.1dev
Summary: Categorize vendor pricelists
Home-page: https://github.com/sygel-technology/sy-purchase-workflow
License: AGPL-3
Author: Sygel,Odoo Community Association - OCA
Classifier: Programming Language :: Python
Classifier: Framework :: Odoo
Classifier: Framework :: Odoo :: 16.0
Classifier: License :: OSI Approved :: GNU Affero General Public License v3
